[
  {
    "file":"20250221092842541",
    "po_match":1,
    "po_gt":"",
    "po_pred":"",
    "line_items_correct":5,
    "line_items_total":5,
    "line_item_accuracy":1.0,
    "totals_match":1,
    "subtotal_gt":51250.0,
    "subtotal_pred":51250.0,
    "vat_gt":10250.0,
    "vat_pred":10250.0,
    "total_gt":61500.0,
    "total_pred":61500.0
  },
  {
    "file":"20250221125114588",
    "po_match":1,
    "po_gt":"PO-135298",
    "po_pred":"PO-135298",
    "line_items_correct":45,
    "line_items_total":45,
    "line_item_accuracy":1.0,
    "totals_match":1,
    "subtotal_gt":885027.92,
    "subtotal_pred":885027.92,
    "vat_gt":177005.58,
    "vat_pred":177005.58,
    "total_gt":1062033.5,
    "total_pred":1062033.5
  },
  {
    "file":"Invaoice_2",
    "po_match":1,
    "po_gt":"PO-360206,PO-362820,PO-526365,PO-620097,PO-756014,PO-842742",
    "po_pred":"PO-360206,PO-362820,PO-526365,PO-620097,PO-756014,PO-842742",
    "line_items_correct":50,
    "line_items_total":50,
    "line_item_accuracy":1.0,
    "totals_match":0,
    "subtotal_gt":11420.61,
    "subtotal_pred":11420.61,
    "vat_gt":2284.12,
    "vat_pred":2284.12,
    "total_gt":13704.73,
    "total_pred":18684.9
  }
]